README.txt
setup.py
docs/HISTORY.txt
docs/INSTALL.txt
docs/LICENSE.GPL
docs/LICENSE.txt
redturtle/__init__.py
redturtle.catalogmount.egg-info/PKG-INFO
redturtle.catalogmount.egg-info/SOURCES.txt
redturtle.catalogmount.egg-info/dependency_links.txt
redturtle.catalogmount.egg-info/entry_points.txt
redturtle.catalogmount.egg-info/namespace_packages.txt
redturtle.catalogmount.egg-info/not-zip-safe
redturtle.catalogmount.egg-info/requires.txt
redturtle.catalogmount.egg-info/top_level.txt
redturtle/catalogmount/__init__.py
redturtle/catalogmount/configure.zcml
redturtle/catalogmount/version.txt
redturtle/catalogmount/Extensions/Install.py
redturtle/catalogmount/Extensions/__init__.py