Metadata-Version: 1.0
Name: redturtle.catalogmount
Version: 0.0.3
Summary: Small package which helps mount portal_catalog to separate ZODB.
Home-page: http://www.redturtle.net
Author: Andrew Mleczko
Author-email: andrew.mleczko@redturtle.net
License: GPL
Keywords: plone ZODB mount Catalog portal_catalog
Platform: UNKNOWN
Classifier: Framework :: Plone
Classifier: Programming Language :: Python
Classifier: Topic :: Software Development :: Libraries :: Python Modules
